mtaf/ADB.py
mtaf/Fastboot.py
mtaf/__init__.py
mtaf/android_actions.py
mtaf/android_zpath.py
mtaf/angular_actions.py
mtaf/fake_detector.py
mtaf/filters.py
mtaf/inspector.py
mtaf/mtaf_logging.py
mtaf/parse_ids.py
mtaf/prune_db.py
mtaf/selenium_actions.py
mtaf/simple_pj.py
mtaf/sort_steps.py
mtaf/test_result.py
mtaf/tk_simple_dialog.py
mtaf/trace.py
mtaf/user_exception.py
mtaf/wav_audio.py
mtaf/web_inspector.py
mtaf/xml_to_csv.py
mtaf/test/__init__.py
mtaf/test/appium_session.py
mtaf/test/color_test_e7.py
mtaf/test/config_test.py
mtaf/test/cseq_timing.py
mtaf/test/fake_detector_test.py
mtaf/test/filter_test.py
mtaf/test/log_test.py
mtaf/test/microservice_test.py
mtaf/test/tc_loader_test.py
mtaf/test/trace_test.py
mtaf/test/ux_test.py
mtaf/test/zpath_test.py
mtaf/test/features/__init__.py
mtaf/test/features/environment.py
mtaf/test/features/steps/__init__.py
mtaf/test/features/steps/steps.py
mtaf-1.0.47.data/data/mtaf/wav/0.wav
mtaf-1.0.47.data/data/mtaf/wav/0q.wav
mtaf-1.0.47.data/data/mtaf/wav/1.wav
mtaf-1.0.47.data/data/mtaf/wav/1q.wav
mtaf-1.0.47.data/data/mtaf/wav/2.wav
mtaf-1.0.47.data/data/mtaf/wav/2q.wav
mtaf-1.0.47.data/data/mtaf/wav/3.wav
mtaf-1.0.47.data/data/mtaf/wav/3q.wav
mtaf-1.0.47.data/data/mtaf/wav/4.wav
mtaf-1.0.47.data/data/mtaf/wav/4q.wav
mtaf-1.0.47.data/data/mtaf/wav/5.wav
mtaf-1.0.47.data/data/mtaf/wav/5q.wav
mtaf-1.0.47.data/data/mtaf/wav/6.wav
mtaf-1.0.47.data/data/mtaf/wav/6q.wav
mtaf-1.0.47.data/data/mtaf/wav/7.wav
mtaf-1.0.47.data/data/mtaf/wav/7q.wav
mtaf-1.0.47.data/data/mtaf/wav/8.wav
mtaf-1.0.47.data/data/mtaf/wav/8q.wav
mtaf-1.0.47.data/data/mtaf/wav/9.wav
mtaf-1.0.47.data/data/mtaf/wav/9q.wav
mtaf-1.0.47.data/data/mtaf/wav/a440.wav
mtaf-1.0.47.data/data/mtaf/wav/a440q.wav
mtaf-1.0.47.data/data/mtaf/wav/dtmf_0.wav
mtaf-1.0.47.data/data/mtaf/wav/dtmf_1.wav
mtaf-1.0.47.data/data/mtaf/wav/dtmf_2.wav
mtaf-1.0.47.data/data/mtaf/wav/dtmf_3.wav
mtaf-1.0.47.dist-info/METADATA
mtaf-1.0.47.dist-info/RECORD
mtaf-1.0.47.dist-info/WHEEL
mtaf-1.0.47.dist-info/entry_points.txt
mtaf-1.0.47.dist-info/top_level.txt
