Metadata-Version: 2.1
Name: mtaf
Version: 1.0.47
Summary: Mobile Test Automation Framework with Appium Inspector GUI for Android Applications
Home-page: https://github.com/mccrorey48/mtaf
Author: Martin McCrorey
Author-email: martin.mccrorey@verizon.net
License: MIT
Keywords: python,android,appium,selenium,adb,uiautomator,viewer,inspector,gui,locator,screenshot,xpath,resource_id,page object model
Platform: UNKNOWN
Classifier: Programming Language :: Python :: 2.7
Classifier: Natural Language :: English
Classifier: Development Status :: 3 - Alpha
Classifier: Intended Audience :: Developers
Classifier: License :: OSI Approved :: MIT License
Classifier: Operating System :: OS Independent
Classifier: Topic :: Software Development :: Testing
Classifier: Topic :: Software Development :: Quality Assurance
Requires-Dist: Appium-Python-Client (==0.25)
Requires-Dist: babel (==2.6.0)
Requires-Dist: beautifulsoup4 (==4.6.1)
Requires-Dist: behave (==1.2.6)
Requires-Dist: ipaddress (==1.0.22)
Requires-Dist: olefile (==0.44)
Requires-Dist: requests (==2.18.4)
Requires-Dist: Pillow (==4.3.0)
Requires-Dist: psutil (==5.4.6)
Requires-Dist: pymongo (==3.3.1)
Requires-Dist: pyserial (==3.3)
Requires-Dist: PyYAML (==3.12)
Requires-Dist: selenium (==3.8.0)
Requires-Dist: six (==1.11.0)
Requires-Dist: spur (==0.3.20)
Requires-Dist: spur (==0.3.20)
Requires-Dist: tkfilebrowser (==2.2.2)
